workflowy_mcp/__init__.py
workflowy_mcp/__main__.py
workflowy_mcp/config.py
workflowy_mcp/server.py
workflowy_mcp/transport.py
workflowy_mcp/client/__init__.py
workflowy_mcp/client/api_client.py
workflowy_mcp/client/rate_limit.py
workflowy_mcp/client/retry.py
workflowy_mcp/middleware/errors.py
workflowy_mcp/middleware/logging.py
workflowy_mcp/models/__init__.py
workflowy_mcp/models/config.py
workflowy_mcp/models/errors.py
workflowy_mcp/models/node.py
workflowy_mcp/models/requests.py
workflowy_mcp-0.3.3.dist-info/METADATA
workflowy_mcp-0.3.3.dist-info/WHEEL
workflowy_mcp-0.3.3.dist-info/entry_points.txt
workflowy_mcp-0.3.3.dist-info/licenses/LICENSE
workflowy_mcp-0.3.3.dist-info/RECORD
